LICENSE
README.md
setup.py
forge/__init__.py
forge/main.py
forge_ai_cli.egg-info/PKG-INFO
forge_ai_cli.egg-info/SOURCES.txt
forge_ai_cli.egg-info/dependency_links.txt
forge_ai_cli.egg-info/entry_points.txt
forge_ai_cli.egg-info/requires.txt
forge_ai_cli.egg-info/top_level.txt