Metadata-Version: 2.1
Name: forge-ai-cli
Version: 0.1
Summary: A CLI AI Agent to execute shell commands
Home-page: https://github.com/amalvivek/forge-cli
Author: Amal Vivek
Author-email: avivek99@gmail.com
License-File: LICENSE
Requires-Dist: python-dotenv
Requires-Dist: octoai-sdk
